onnxnpu/__init__.py
onnxnpu/checker.py
onnxnpu/cli.py
onnxnpu/optimizer.py
onnxnpu/profiles/KL520.json
onnxnpu/profiles/KL530.json
onnxnpu/profiles/KL630.json
onnxnpu/profiles/KL720.json
onnxnpu/profiles/KL730.json
onnxnpu-0.2.0.dist-info/licenses/LICENSE
onnxnpu-0.2.0.dist-info/METADATA
onnxnpu-0.2.0.dist-info/WHEEL
onnxnpu-0.2.0.dist-info/entry_points.txt
onnxnpu-0.2.0.dist-info/top_level.txt
onnxnpu-0.2.0.dist-info/RECORD
