Metadata-Version: 2.4
Name: onnxnpu
Version: 0.2.0
Summary: An open-source, lightweight CLI utility for ONNX model compatibility validation and performance optimization on Kneron NPUs
Maintainer-email: Mason Huang <masonhuang0320@gmail.com>
License: Apache-2.0
Project-URL: homepage, https://github.com/HuangMason320/onnxnpu-toolkit
Project-URL: repository, https://github.com/HuangMason320/onnxnpu-toolkit
Requires-Python: <3.12,>=3.9
License-File: LICENSE
Requires-Dist: onnx>=1.17.0
Requires-Dist: onnxruntime>=1.20.1
Requires-Dist: onnxsim>=0.4.36
Dynamic: license-file
